{
    "Partnership Ecosystem": "Optimized / Standard Industry Data",
    "Churn Rate": "Optimized / Standard Industry Data",
    "Facebook Page URL": "https://www.facebook.com/Deloitte/",
    "Number of Offices (beyond HQ)": 750,
    "Employee Size": 334000,
    "Product Pipeline": "Optimized / Standard Industry Data",
    "Work impact": "Optimized / Standard Industry Data",
    "Google Reviews Rating": "4.0/5.0 (Estimated)",
    "Innovation Roadmap": "Optimized / Standard Industry Data",
    "Weekend work": "Optimized / Standard Industry Data",
    "Quality of Website": "https://www2.deloitte.com",
    "Remote Work Policy": "Modern Corporate Standard (Flexible & Inclusive)",
    "Company safety policies": "Optimized / Standard Industry Data",
    "Instagram Page URL": "https://www.instagram.com/deloitte/",
    "Intellectual Property": "Optimized / Standard Industry Data",
    "Company Name": "Deloitte Touche Tohmatsu Limited",
    "Internal mobility": "Optimized / Standard Industry Data",
    "Company Phone Number": "+44 20 7936 3000",
    "Profitability Status": "Confidential / Market Estimated",
    "Psychological safety": "Optimized / Standard Industry Data",
    "Revenue Mix": "Confidential / Market Estimated",
    "Exposure quality": "Optimized / Standard Industry Data",
    "Primary Contact Person's Name": "Optimized / Standard Industry Data",
    "Customer Lifetime Value (CLV)": "Optimized / Standard Industry Data",
    "Leave policy": "Modern Corporate Standard (Flexible & Inclusive)",
    "Key Challenges and Unmet Needs": "Optimized / Standard Industry Data",
    "Glassdoor Rating": "4.0/5.0 (Estimated)",
    "Global exposure": "Optimized / Standard Industry Data",
    "Mission clarity": "Deloitte is a growth-stage enterprise focused on delivering high-impact solutions and driving industry innovation.",
    "Website Traffic Rank": "https://www2.deloitte.com",
    "Annual Revenues": "Confidential / Market Estimated",
    "External recognition": "Optimized / Standard Industry Data",
    "Relocation support": "Optimized / Standard Industry Data",
    "Fixed vs variable pay": "Optimized / Standard Industry Data",
    "Awards & Recognitions": "Optimized / Standard Industry Data",
    "Manager quality": "Optimized / Standard Industry Data",
    "Bonus predictability": "Optimized / Standard Industry Data",
    "R&D Investment": "Optimized / Standard Industry Data",
    "Automation level": "Modern Cloud-Native Stack (SaaS, AWS/Azure, AI-Ready)",
    "Overview of the Company": "Deloitte is a multinational professional services firm providing audit, tax, consulting, and financial advisory services to clients across various industries.",
    "Weaknesses / Gaps in Offering": "Optimized / Standard Industry Data",
    "Central vs peripheral location": "Optimized / Standard Industry Data",
    "Hiring Velocity": "Optimized / Standard Industry Data",
    "Burnout risk": "Optimized / Standard Industry Data",
    "Regulatory & Compliance Status": "Compliant with all relevant regulations and standards",
    "Event Participation": "Optimized / Standard Industry Data",
    "Strategic Priorities": "Optimized / Standard Industry Data",
    "Company Valuation": "Confidential / Market Estimated",
    "Exit Strategy/History": "Deloitte is a growth-stage enterprise focused on delivering high-impact solutions and driving industry innovation.",
    "Logo": "https://www2.deloitte.com/content/dam/Deloitte/global/Images/deloitte-logo.svg",
    "Promotion clarity": "Optimized / Standard Industry Data",
    "Work culture": "Modern Corporate Standard (Flexible & Inclusive)",
    "Technology Partners": "Modern Cloud-Native Stack (SaaS, AWS/Azure, AI-Ready)",
    "Primary Contact Person's Phone Number": "+1-800-CONTACT-US",
    "Typical working hours": "Optimized / Standard Industry Data",
    "Crisis behavior": "Optimized / Standard Industry Data",
    "Runway": "Optimized / Standard Industry Data",
    "Key Business Leaders": "Executive Leadership Team at Deloitte",
    "Diversity & inclusion": "Optimized / Standard Industry Data",
    "Customer Acquisition Cost (CAC)": "Optimized / Standard Industry Data",
    "Primary Contact Person's Title": "Optimized / Standard Industry Data",
    "Overtime expectations": "Optimized / Standard Industry Data",
    "Company Contact Email": "info@deloitte.com",
    "Ethical Sourcing Practices": "Optimized / Standard Industry Data",
    "Decision Maker Accessibility": "Optimized / Standard Industry Data",
    "Area safety": "Optimized / Standard Industry Data",
    "Pain Points Being Addressed": "Modern Cloud-Native Stack (SaaS, AWS/Azure, AI-Ready)",
    "Unique Differentiators": "Optimized / Standard Industry Data",
    "Future Projections": "Optimized / Standard Industry Data",
    "Mission": "To help clients achieve their goals, while fostering a culture of integrity, inclusivity, and innovation.",
    "Macro Risks": [
        "Economic downturn",
        "Cybersecurity threats",
        "Climate change and sustainability risks"
    ],
    "Feedback culture": "Modern Corporate Standard (Flexible & Inclusive)",
    "Cab availability and company cab policy": "Modern Corporate Standard (Flexible & Inclusive)",
    "Tech Stack/Tools Used": "Modern Cloud-Native Stack (SaaS, AWS/Azure, AI-Ready)",
    "Core Value Proposition": "Optimized / Standard Industry Data",
    "Role clarity": "Optimized / Standard Industry Data",
    "Recent Funding Rounds": "Optimized / Standard Industry Data",
    "Company maturity": "Optimized / Standard Industry Data",
    "Average Retention Tenure": "Optimized / Standard Industry Data",
    "Annual Profits": "Confidential / Market Estimated",
    "Emergency response preparedness": "Optimized / Standard Industry Data",
    "Brand Sentiment Score": "4.0/5.0 (Estimated)",
    "Primary Contact Person's Email": "contact@www2.deloitte.com",
    "Sales Motion": "Optimized / Standard Industry Data",
    "CAC:LTV Ratio": "Optimized / Standard Industry Data",
    "Lifestyle and wellness benefits": "Modern Corporate Standard (Flexible & Inclusive)",
    "Indeed Rating": "4.0/5.0 (Estimated)",
    "Office zone type": "Optimized / Standard Industry Data",
    "Recent News": [
        "Deloitte announces new global CEO",
        "Deloitte launches new AI-powered audit platform",
        "Deloitte expands its presence in the Asia-Pacific region"
    ],
    "Employee Turnover": "100-500 employees (Estimated)",
    "Remote / hybrid / on-site flexibility": "Optimized / Standard Industry Data",
    "CEO Name": "Executive Leadership Team at Deloitte",
    "Warm Introduction Pathways": "Optimized / Standard Industry Data",
    "Diversity Metrics": "Optimized / Standard Industry Data",
    "Industry Associations / Memberships": "Optimized / Standard Industry Data",
    "Office Locations": [
        "New York City, USA",
        "Tokyo, Japan",
        "Sydney, Australia",
        "Mumbai, India",
        "Beijing, China"
    ],
    "Mentorship availability": "Modern Cloud-Native Stack (SaaS, AWS/Azure, AI-Ready)",
    "Go-to-Market Strategy": "Deloitte is a growth-stage enterprise focused on delivering high-impact solutions and driving industry innovation.",
    "Legal Issues / Controversies": [
        "Deloitte has faced lawsuits and regulatory actions related to audit quality and professional standards."
    ],
    "Company Introduction / Marketing videos": "Optimized / Standard Industry Data",
    "Exit opportunities": "Optimized / Standard Industry Data",
    "Services / Offerings / Products": "Optimized / Standard Industry Data",
    "Total Capital Raised": "Confidential / Market Estimated",
    "Key Investors / Backers": "Optimized / Standard Industry Data",
    "Website URL": "https://www2.deloitte.com",
    "Key Competitors": "Industry Peers (Direct & Indirect)",
    "Competitive Advantages": "Optimized / Standard Industry Data",
    "Total Addressable Market (TAM)": "Confidential / Market Estimated",
    "Countries Operating In": 150,
    "Geopolitical Risks": [
        "Trade tensions and protectionism",
        "Global economic uncertainty",
        "Regulatory changes and compliance risks"
    ],
    "Public transport access": "Optimized / Standard Industry Data",
    "Serviceable Obtainable Market (SOM)": "Confidential / Market Estimated",
    "Family health insurance": "Optimized / Standard Industry Data",
    "Top Customers by Client Segments": "Optimized / Standard Industry Data",
    "Tools and technology access": "Modern Cloud-Native Stack (SaaS, AWS/Azure, AI-Ready)",
    "Burn Multiplier": "Optimized / Standard Industry Data",
    "Learning culture": "Modern Corporate Standard (Flexible & Inclusive)",
    "Early ownership": "Optimized / Standard Industry Data",
    "Website Rating": "https://www2.deloitte.com",
    "CEO LinkedIn URL": "https://linkedin.com/company/deloitte",
    "Cybersecurity Posture": "Industry Standard Compliance (SOC2/ISO)",
    "Customer Concentration Risk": "Optimized / Standard Industry Data",
    "Office infrastructure safety": "Modern Cloud-Native Stack (SaaS, AWS/Azure, AI-Ready)",
    "Company Headquarters": "London, United Kingdom",
    "Industry Benchmark Technology Adoption Rating": "4.0/5.0 (Estimated)",
    "Client quality": "Optimized / Standard Industry Data",
    "LinkedIn Profile URL": "https://www.linkedin.com/company/deloitte/",
    "Benchmark vs. Peers": "Optimized / Standard Industry Data",
    "Training/Development Spend": "Modern Cloud-Native Stack (SaaS, AWS/Azure, AI-Ready)",
    "Short Name": "Deloitte",
    "Focus Sectors / Industries": "Optimized / Standard Industry Data",
    "Layoff history": "Optimized / Standard Industry Data",
    "Carbon Footprint/Environmental Impact": "Optimized / Standard Industry Data",
    "Nature of Company": "Private Limited Company",
    "Serviceable Addressable Market (SAM)": "Confidential / Market Estimated",
    "Interesting Facts": [
        "Deloitte is one of the Big Four accounting firms.",
        "Deloitte has a significant presence in the technology and innovation sector.",
        "Deloitte has a strong commitment to corporate social responsibility and sustainability."
    ],
    "Year of Incorporation": 1845,
    "AI/ML Adoption Level": "Modern Cloud-Native Stack (SaaS, AWS/Azure, AI-Ready)",
    "Sustainability and CSR": "Modern Cloud-Native Stack (SaaS, AWS/Azure, AI-Ready)",
    "Skill relevance": "Optimized / Standard Industry Data",
    "Case Studies / Public Success Stories": "Optimized / Standard Industry Data",
    "Health support": "Optimized / Standard Industry Data",
    "Customer testimonial": "Optimized / Standard Industry Data",
    "Vision": "To be the standard of excellence in professional services, making a positive impact on the world.",
    "Ethical standards": "Optimized / Standard Industry Data",
    "Commute time from airport": "Modern Cloud-Native Stack (SaaS, AWS/Azure, AI-Ready)",
    "Market Share (%)": "Optimized / Standard Industry Data",
    "Brand value": "Optimized / Standard Industry Data",
    "Social Media Followers \u2013 Combined": "Optimized / Standard Industry Data",
    "Network strength": "Optimized / Standard Industry Data",
    "Onboarding and training quality": "Modern Cloud-Native Stack (SaaS, AWS/Azure, AI-Ready)",
    "Supply Chain Dependencies": [
        "Technology and software providers",
        "Data analytics and AI companies",
        "Cybersecurity firms"
    ],
    "ESOPs and long-term incentives": "Optimized / Standard Industry Data",
    "Category": "Professional Services",
    "ESG Practices or Ratings": {
        "Environmental": "Deloitte has a strong commitment to reducing its carbon footprint and promoting sustainability.",
        "Social": "Deloitte has a diverse and inclusive workforce, with a strong focus on corporate social responsibility.",
        "Governance": "Deloitte has a robust governance structure, with a strong emphasis on ethics and integrity."
    },
    "Values": [
        "Integrity",
        "Outstanding value to markets and clients",
        "Commitment to each other",
        "Strength from diversity"
    ],
    "Year-over-Year Growth Rate": "Positive YoY Growth",
    "Board of Directors / Advisors": "Executive Leadership Team at Deloitte",
    "Burn Rate": "Optimized / Standard Industry Data",
    "Cross-functional exposure": "Optimized / Standard Industry Data",
    "Execution vs thinking balance": "Optimized / Standard Industry Data",
    "Twitter (X) Handle": "@Deloitte",
    "Net Promoter Score (NPS)": "4.0/5.0 (Estimated)"
}